web_engine/__init__.py
web_engine/__main__.py
web_engine/harvesting.py
web_engine/converting/__init__.py
web_engine/converting/htmldocx.py
web_engine/converting/pdfkit.py
web_engine/converting/weasyprint.py
web_engine/converting/wkhtmltopdf.py
web_engine/merging/PyPDF2.py
web_engine/merging/__init__.py
web_engine/merging/pypdf.py
web_engine-0.1.0.dist-info/LICENSE.txt
web_engine-0.1.0.dist-info/METADATA
web_engine-0.1.0.dist-info/WHEEL
web_engine-0.1.0.dist-info/top_level.txt
web_engine-0.1.0.dist-info/RECORD
