Metadata-Version: 2.1
Name: web-engine
Version: 0.1.0
Summary: Websites to PDFs.
Author-email: Johannes <johannes-programming@posteo.org>
License: The MIT License (MIT)
Project-URL: Download, https://pypi.org/project/web-engine/#files
Project-URL: Source, https://github.com/johannes-programming/web_engine
Classifier: License :: OSI Approved :: MIT License
Classifier: Programming Language :: Python
Classifier: Programming Language :: Python :: 3
Requires-Python: >=3.11
License-File: LICENSE.txt
Requires-Dist: PyPDF2
Requires-Dist: pdfkit
Requires-Dist: pypdf
Requires-Dist: wkhtmltopdf
Requires-Dist: docx2pdf
Requires-Dist: htmldocx
Requires-Dist: weasyprint
